{"bestiary_archimax.md":"Bwzyhvkp","bestiary_archimedean.md":"aCHzBQ0I","bestiary_elliptical.md":"B3PDQeRL","bestiary_empirical.md":"9jfYeRyA","bestiary_extremevalues.md":"DV5L3CwP","bestiary_indep_and_fh_bouds.md":"CPAbN0hv","bestiary_miscellaneous.md":"Be39tJ3M","bestiary_transformations.md":"COXrAI4Q","examples_archimedean_radial_estimation.md":"B4xc7g2o","examples_fitting_sklar.md":"CLfXOjrh","examples_ifm1.md":"BReNei-7","examples_lambda_viz.md":"B7y2PKbB","examples_lossalae.md":"DF1pP-bO","examples_other_usecases.md":"C3PP_y2b","examples_turing.md":"YvCrTmmd","idx.md":"cIu71EuA","index.md":"CBT8sYvg","manual_archimax.md":"CFvhybr_","manual_archimedean.md":"pGta_-UX","manual_conditioning_and_subsetting.md":"caupfoxZ","manual_dependence_measures.md":"DDeTHP8z","manual_elliptical.md":"DpUVV6FR","manual_empirical.md":"B_FfmA8D","manual_extremevalues.md":"BTs-73gf","manual_getting_started.md":"CA_8lXGG","manual_sklar.md":"CKJxsQDx","manual_troubleshooting.md":"mkfnwf-a","manual_vines.md":"DgRe_U8V","manual_visualizations.md":"Df0mEMhJ","references.md":"QdsbELWB"}
