{"api_internal.md":"CGOb1e_p","api_public.md":"ByRMf9ON","bestiary_archimax.md":"D9Wqjio3","bestiary_archimedean.md":"Bs4GXC7e","bestiary_elliptical.md":"B9mQlZ-L","bestiary_empirical.md":"DZ_iQozp","bestiary_extremevalues.md":"DrSvyx57","bestiary_miscellaneous.md":"DHcN-cMu","bestiary_vines.md":"DRDPWakh","examples_archimedean_radial_estimation.md":"CQod7xtE","examples_fitting_sklar.md":"C5eaaTuW","examples_ifm1.md":"E-ZupRNk","examples_lambda_viz.md":"BlsOaLhg","examples_lossalae.md":"Dh8zUo5W","examples_other_usecases.md":"Dpf6T03v","examples_turing.md":"411OsLGI","index.md":"DAH4Auww","manual_conditioning_and_subsetting.md":"DU16lweq","manual_dependence_measures.md":"0vyseVpL","manual_developer_guide.md":"BKOrxxI8","manual_fitting_interface.md":"hDjCwILW","manual_intro.md":"nGX9nXH2","manual_visualizations.md":"DB2RAvzM","references.md":"DKLhhsxS"}
