{"api_internal.md":"QZ_ynxVQ","api_public.md":"BnNcHu0J","bestiary_archimax.md":"B5X5vw1s","bestiary_archimedean.md":"5ySQ-bZk","bestiary_elliptical.md":"CZiYQnWq","bestiary_empirical.md":"GeoIYDUj","bestiary_extremevalues.md":"CiubGpQi","bestiary_miscellaneous.md":"7NDLEPiS","bestiary_vines.md":"0yM149X5","examples_archimedean_radial_estimation.md":"CyBmm6oj","examples_fitting_sklar.md":"B6yZo_jl","examples_ifm1.md":"DNa8qfYa","examples_lambda_viz.md":"DAuFIUVJ","examples_lossalae.md":"B4GTTwl6","examples_other_usecases.md":"qrZG3zdT","examples_turing.md":"BUd-VIGO","index.md":"CbklqMZM","manual_conditioning_and_subsetting.md":"YSdQ2mvT","manual_dependence_measures.md":"CiW8woVR","manual_fitting_interface.md":"CoRXnJmI","manual_intro.md":"qvqqclzZ","manual_visualizations.md":"mBMxiDFQ","references.md":"C-nkevkq"}
