{"api_internal.md":"BjOpmNei","api_public.md":"Av-GIhxp","bestiary_archimax.md":"BZ7SJlcY","bestiary_archimedean.md":"DI0S43Y8","bestiary_elliptical.md":"BLfQM32s","bestiary_empirical.md":"Dhu7DxUf","bestiary_extremevalues.md":"CErro705","bestiary_miscellaneous.md":"DqPrf7Is","bestiary_vines.md":"CKfloMqg","examples_archimedean_radial_estimation.md":"D19b6tWG","examples_fitting_sklar.md":"DzavBQJx","examples_ifm1.md":"17tmnm8e","examples_lambda_viz.md":"fEzvaW_S","examples_lossalae.md":"FU_-UOCh","examples_other_usecases.md":"BIm6qsLv","examples_turing.md":"DRIkCohl","index.md":"D5uBESIj","manual_conditioning_and_subsetting.md":"BV_1FiLV","manual_dependence_measures.md":"CvWZLwK8","manual_fitting_interface.md":"C6vnPl4_","manual_intro.md":"Bq7q5xo1","manual_visualizations.md":"BBELjNou","references.md":"ToVE6LZp"}
